LICENSE.txt
MANIFEST.in
README.md
requirements.txt
setup.py
docs/DEV.md
lib/__init__.py
lib/convert.py
lib/p4info_helper.py
ovs_p4/__init__.py
ovs_p4/ovs_p4.py
ovs_p4.egg-info/PKG-INFO
ovs_p4.egg-info/SOURCES.txt
ovs_p4.egg-info/dependency_links.txt
ovs_p4.egg-info/entry_points.txt
ovs_p4.egg-info/requires.txt
ovs_p4.egg-info/top_level.txt
ovs_p4/drivers/__init__.py
ovs_p4/drivers/driver.py
ovs_p4/drivers/ovs/__init__.py
ovs_p4/drivers/ovs/exceptions.py
ovs_p4/drivers/ovs/ovs_driver.py
ovs_p4/engine/__init__.py
ovs_p4/engine/engine.py
ovs_p4/engine/db/__init__.py
ovs_p4/engine/db/connector.py
ovs_p4/engine/db/model.py
ovs_p4/engine/handlers/__init__.py
ovs_p4/engine/handlers/abstract.py
ovs_p4/engine/handlers/get_fwd_pipeline_config.py
ovs_p4/engine/handlers/read.py
ovs_p4/engine/handlers/set_fwd_pipeline_config.py
ovs_p4/engine/handlers/write.py
ovs_p4/engine/utils/__init__.py
ovs_p4/engine/utils/util.py
ovs_p4/p4runtime/__init__.py
ovs_p4/p4runtime/server.py
ovs_p4/p4runtime/service.py
p4_ctl/__init__.py
p4_ctl/p4_ctl.py
p4_ctl/client/__init__.py
p4_ctl/client/p4rt_client.py
p4_ctl/commands/__init__.py
p4_ctl/commands/command.py
p4_ctl/commands/get_config_command.py
p4_ctl/commands/load_config_command.py
p4_ctl/commands/table_dump_command.py
p4_ctl/commands/table_update_command.py
p4_ctl/receivers/__init__.py
p4_ctl/receivers/get_config.py
p4_ctl/receivers/load_config.py
p4_ctl/receivers/table_dump.py
p4_ctl/receivers/table_update.py
proto/p4runtime.proto
scripts/__init__.py
scripts/install_p4runtime.sh
scripts/grpc-v1.3.2-patches-for-ubuntu18.04/add-wrap-memcpy-flags.diff
scripts/grpc-v1.3.2-patches-for-ubuntu18.04/fix-libgrpc++-soname.diff
scripts/grpc-v1.3.2-patches-for-ubuntu18.04/make-pkg-config-files-nonexecutable.diff
scripts/grpc-v1.3.2-patches-for-ubuntu18.04/no-werror.diff
scripts/grpc-v1.3.2-patches-for-ubuntu18.04/unvendor-zlib.diff