Metadata-Version: 2.1
Name: ovs-p4
Version: 0.0.2
Summary: The package contains a P4Runtime server for P4 capable ovs switch and a ovs-p4ctl command line tool for monitoring and administering
Home-page: UNKNOWN
Author: Tomasz Osinski, Mateusz Kossakowski
Author-email: osinstom@gmail.com, mateusz.kossakowski.10@gmail.com
License: UNKNOWN
Platform: UNKNOWN
Classifier: Programming Language :: Python :: 2
Classifier: License :: OSI Approved :: Apache Software License
Classifier: Operating System :: OS Independent
Requires-Python: >=2.7
